{"CSS":"style.css","Preview":"\/tmp\/fonts4web\/\/lukey@snails.email\/1507304318.1509\/c8572c769e7a5eb1add466705c68c331\/Preview for Labtop Unicase.png","NameCard":"font-name-card.png","FontType":"TrueType","FontCopyright":"Generated by Fonts 4 Web (http:\/\/fonts4web.org.uk) on behalf of:Company: Lukey ShawName: Lukey ShaweMail: lukey@snails.emailThis is licensed under Creative Commons - Share Alike which legal transcript can be found at: https:\/\/creativecommons.org\/licenses\/by-sa\/4.0\/legalcode","FontName":"Labtop Unicase","FontSubfamily":"Book","FontSubfamilyID":"FontForge 2.0 : Labtop Unicase : 9-8-2017","FontFullName":"Labtop Unicase","FontVersion":"Version 2.227 ","FontWeight":null,"FontPostscriptName":"labtopunicase","Files":{"\/ACADEMIC":"\/ACADEMIC","\/LICENSE":"\/LICENSE","\/Labtop Unicase.afm":"\/Labtop Unicase.afm","\/Labtop Unicase.bin":"\/Labtop Unicase.bin","\/Labtop Unicase.cef":"\/Labtop Unicase.cef","\/Labtop Unicase.cff":"\/Labtop Unicase.cff","\/Labtop Unicase.dfont":"\/Labtop Unicase.dfont","\/Labtop Unicase.eot":"\/Labtop Unicase.eot","\/Labtop Unicase.fon":"\/Labtop Unicase.fon","\/Labtop Unicase.gai":"\/Labtop Unicase.gai","\/Labtop Unicase.gsf":"\/Labtop Unicase.gsf","\/Labtop Unicase.hqx":"\/Labtop Unicase.hqx","\/Labtop Unicase.ik":"\/Labtop Unicase.ik","\/Labtop Unicase.mf":"\/Labtop Unicase.mf","\/Labtop Unicase.otf":"\/Labtop Unicase.otf","\/Labtop Unicase.pcf":"\/Labtop Unicase.pcf","\/Labtop Unicase.pf3":"\/Labtop Unicase.pf3","\/Labtop Unicase.pfa":"\/Labtop Unicase.pfa","\/Labtop Unicase.pfb":"\/Labtop Unicase.pfb","\/Labtop Unicase.pmf":"\/Labtop Unicase.pmf","\/Labtop Unicase.pt3":"\/Labtop Unicase.pt3","\/Labtop Unicase.sfd":"\/Labtop Unicase.sfd","\/Labtop Unicase.svg":"\/Labtop Unicase.svg","\/Labtop Unicase.t42":"\/Labtop Unicase.t42","\/Labtop Unicase.ttd":"\/Labtop Unicase.ttd","\/Labtop Unicase.ttf":"\/Labtop Unicase.ttf","\/Labtop Unicase.ttg":"\/Labtop Unicase.ttg","\/Labtop Unicase.ufm":"\/Labtop Unicase.ufm","\/Labtop Unicase.woff":"\/Labtop Unicase.woff","\/Preview for Labtop Unicase.png":"\/Preview for Labtop Unicase.png","\/code128-barcode-e42wo.jpg":"\/code128-barcode-e42wo.jpg","\/code128-referee-q53wakyemyk.jpg":"\/code128-referee-q53wakyemyk.jpg","\/font-name-card.png":"\/font-name-card.png","\/style.css":"\/style.css","\/Labtop Unicase.ufo\/feature.fea":"\/Labtop Unicase.ufo\/feature.fea","\/Labtop Unicase.ufo\/fontinfo.plist":"\/Labtop Unicase.ufo\/fontinfo.plist","\/Labtop Unicase.ufo\/groups.plist":"\/Labtop Unicase.ufo\/groups.plist","\/Labtop Unicase.ufo\/kerning.plist":"\/Labtop Unicase.ufo\/kerning.plist","\/Labtop Unicase.ufo\/metainfo.plist":"\/Labtop Unicase.ufo\/metainfo.plist","\/Labtop Unicase.ufo\/glyphs\/A_.glif":"\/Labtop Unicase.ufo\/glyphs\/A_.glif","\/Labtop Unicase.ufo\/glyphs\/A_E_.glif":"\/Labtop Unicase.ufo\/glyphs\/A_E_.glif","\/Labtop Unicase.ufo\/glyphs\/A_acute.glif":"\/Labtop Unicase.ufo\/glyphs\/A_acute.glif","\/Labtop Unicase.ufo\/glyphs\/A_circumflex.glif":"\/Labtop Unicase.ufo\/glyphs\/A_circumflex.glif","\/Labtop Unicase.ufo\/glyphs\/A_dieresis.glif":"\/Labtop Unicase.ufo\/glyphs\/A_dieresis.glif","\/Labtop Unicase.ufo\/glyphs\/A_grave.glif":"\/Labtop Unicase.ufo\/glyphs\/A_grave.glif","\/Labtop Unicase.ufo\/glyphs\/A_ring.glif":"\/Labtop Unicase.ufo\/glyphs\/A_ring.glif","\/Labtop Unicase.ufo\/glyphs\/A_tilde.glif":"\/Labtop Unicase.ufo\/glyphs\/A_tilde.glif","\/Labtop Unicase.ufo\/glyphs\/B_.glif":"\/Labtop Unicase.ufo\/glyphs\/B_.glif","\/Labtop Unicase.ufo\/glyphs\/C_.glif":"\/Labtop Unicase.ufo\/glyphs\/C_.glif","\/Labtop Unicase.ufo\/glyphs\/C_cedilla.glif":"\/Labtop Unicase.ufo\/glyphs\/C_cedilla.glif","\/Labtop Unicase.ufo\/glyphs\/D_.glif":"\/Labtop Unicase.ufo\/glyphs\/D_.glif","\/Labtop Unicase.ufo\/glyphs\/E_.glif":"\/Labtop Unicase.ufo\/glyphs\/E_.glif","\/Labtop Unicase.ufo\/glyphs\/E_acute.glif":"\/Labtop Unicase.ufo\/glyphs\/E_acute.glif","\/Labtop Unicase.ufo\/glyphs\/E_circumflex.glif":"\/Labtop Unicase.ufo\/glyphs\/E_circumflex.glif","\/Labtop Unicase.ufo\/glyphs\/E_dieresis.glif":"\/Labtop Unicase.ufo\/glyphs\/E_dieresis.glif","\/Labtop Unicase.ufo\/glyphs\/E_grave.glif":"\/Labtop Unicase.ufo\/glyphs\/E_grave.glif","\/Labtop Unicase.ufo\/glyphs\/E_th.glif":"\/Labtop Unicase.ufo\/glyphs\/E_th.glif","\/Labtop Unicase.ufo\/glyphs\/F_.glif":"\/Labtop Unicase.ufo\/glyphs\/F_.glif","\/Labtop Unicase.ufo\/glyphs\/G_.glif":"\/Labtop Unicase.ufo\/glyphs\/G_.glif","\/Labtop Unicase.ufo\/glyphs\/H_.glif":"\/Labtop Unicase.ufo\/glyphs\/H_.glif","\/Labtop Unicase.ufo\/glyphs\/I_.glif":"\/Labtop Unicase.ufo\/glyphs\/I_.glif","\/Labtop Unicase.ufo\/glyphs\/I_acute.glif":"\/Labtop Unicase.ufo\/glyphs\/I_acute.glif","\/Labtop Unicase.ufo\/glyphs\/I_circumflex.glif":"\/Labtop Unicase.ufo\/glyphs\/I_circumflex.glif","\/Labtop Unicase.ufo\/glyphs\/I_dieresis.glif":"\/Labtop Unicase.ufo\/glyphs\/I_dieresis.glif","\/Labtop Unicase.ufo\/glyphs\/I_grave.glif":"\/Labtop Unicase.ufo\/glyphs\/I_grave.glif","\/Labtop Unicase.ufo\/glyphs\/J_.glif":"\/Labtop Unicase.ufo\/glyphs\/J_.glif","\/Labtop Unicase.ufo\/glyphs\/K_.glif":"\/Labtop Unicase.ufo\/glyphs\/K_.glif","\/Labtop Unicase.ufo\/glyphs\/L_.glif":"\/Labtop Unicase.ufo\/glyphs\/L_.glif","\/Labtop Unicase.ufo\/glyphs\/L_slash.glif":"\/Labtop Unicase.ufo\/glyphs\/L_slash.glif","\/Labtop Unicase.ufo\/glyphs\/M_.glif":"\/Labtop Unicase.ufo\/glyphs\/M_.glif","\/Labtop Unicase.ufo\/glyphs\/N_.glif":"\/Labtop Unicase.ufo\/glyphs\/N_.glif","\/Labtop Unicase.ufo\/glyphs\/N_tilde.glif":"\/Labtop Unicase.ufo\/glyphs\/N_tilde.glif","\/Labtop Unicase.ufo\/glyphs\/O_.glif":"\/Labtop Unicase.ufo\/glyphs\/O_.glif","\/Labtop Unicase.ufo\/glyphs\/O_E_.glif":"\/Labtop Unicase.ufo\/glyphs\/O_E_.glif","\/Labtop Unicase.ufo\/glyphs\/O_acute.glif":"\/Labtop Unicase.ufo\/glyphs\/O_acute.glif","\/Labtop Unicase.ufo\/glyphs\/O_circumflex.glif":"\/Labtop Unicase.ufo\/glyphs\/O_circumflex.glif","\/Labtop Unicase.ufo\/glyphs\/O_dieresis.glif":"\/Labtop Unicase.ufo\/glyphs\/O_dieresis.glif","\/Labtop Unicase.ufo\/glyphs\/O_grave.glif":"\/Labtop Unicase.ufo\/glyphs\/O_grave.glif","\/Labtop Unicase.ufo\/glyphs\/O_slash.glif":"\/Labtop Unicase.ufo\/glyphs\/O_slash.glif","\/Labtop Unicase.ufo\/glyphs\/O_tilde.glif":"\/Labtop Unicase.ufo\/glyphs\/O_tilde.glif","\/Labtop Unicase.ufo\/glyphs\/P_.glif":"\/Labtop Unicase.ufo\/glyphs\/P_.glif","\/Labtop Unicase.ufo\/glyphs\/Q_.glif":"\/Labtop Unicase.ufo\/glyphs\/Q_.glif","\/Labtop Unicase.ufo\/glyphs\/R_.glif":"\/Labtop Unicase.ufo\/glyphs\/R_.glif","\/Labtop Unicase.ufo\/glyphs\/S_.glif":"\/Labtop Unicase.ufo\/glyphs\/S_.glif","\/Labtop Unicase.ufo\/glyphs\/S_caron.glif":"\/Labtop Unicase.ufo\/glyphs\/S_caron.glif","\/Labtop Unicase.ufo\/glyphs\/T_.glif":"\/Labtop Unicase.ufo\/glyphs\/T_.glif","\/Labtop Unicase.ufo\/glyphs\/T_horn.glif":"\/Labtop Unicase.ufo\/glyphs\/T_horn.glif","\/Labtop Unicase.ufo\/glyphs\/U_.glif":"\/Labtop Unicase.ufo\/glyphs\/U_.glif","\/Labtop Unicase.ufo\/glyphs\/U_acute.glif":"\/Labtop Unicase.ufo\/glyphs\/U_acute.glif","\/Labtop Unicase.ufo\/glyphs\/U_circumflex.glif":"\/Labtop Unicase.ufo\/glyphs\/U_circumflex.glif","\/Labtop Unicase.ufo\/glyphs\/U_dieresis.glif":"\/Labtop Unicase.ufo\/glyphs\/U_dieresis.glif","\/Labtop Unicase.ufo\/glyphs\/U_grave.glif":"\/Labtop Unicase.ufo\/glyphs\/U_grave.glif","\/Labtop Unicase.ufo\/glyphs\/V_.glif":"\/Labtop Unicase.ufo\/glyphs\/V_.glif","\/Labtop Unicase.ufo\/glyphs\/W_.glif":"\/Labtop Unicase.ufo\/glyphs\/W_.glif","\/Labtop Unicase.ufo\/glyphs\/X_.glif":"\/Labtop Unicase.ufo\/glyphs\/X_.glif","\/Labtop Unicase.ufo\/glyphs\/Y_.glif":"\/Labtop Unicase.ufo\/glyphs\/Y_.glif","\/Labtop Unicase.ufo\/glyphs\/Y_acute.glif":"\/Labtop Unicase.ufo\/glyphs\/Y_acute.glif","\/Labtop Unicase.ufo\/glyphs\/Y_dieresis.glif":"\/Labtop Unicase.ufo\/glyphs\/Y_dieresis.glif","\/Labtop Unicase.ufo\/glyphs\/Z_.glif":"\/Labtop Unicase.ufo\/glyphs\/Z_.glif","\/Labtop Unicase.ufo\/glyphs\/Z_caron.glif":"\/Labtop Unicase.ufo\/glyphs\/Z_caron.glif","\/Labtop Unicase.ufo\/glyphs\/_notdef.glif":"\/Labtop Unicase.ufo\/glyphs\/_notdef.glif","\/Labtop Unicase.ufo\/glyphs\/_null.glif":"\/Labtop Unicase.ufo\/glyphs\/_null.glif","\/Labtop Unicase.ufo\/glyphs\/a.glif":"\/Labtop Unicase.ufo\/glyphs\/a.glif","\/Labtop Unicase.ufo\/glyphs\/aacute.glif":"\/Labtop Unicase.ufo\/glyphs\/aacute.glif","\/Labtop Unicase.ufo\/glyphs\/acircumflex.glif":"\/Labtop Unicase.ufo\/glyphs\/acircumflex.glif","\/Labtop Unicase.ufo\/glyphs\/acute.glif":"\/Labtop Unicase.ufo\/glyphs\/acute.glif","\/Labtop Unicase.ufo\/glyphs\/adieresis.glif":"\/Labtop Unicase.ufo\/glyphs\/adieresis.glif","\/Labtop Unicase.ufo\/glyphs\/ae.glif":"\/Labtop Unicase.ufo\/glyphs\/ae.glif","\/Labtop Unicase.ufo\/glyphs\/agrave.glif":"\/Labtop Unicase.ufo\/glyphs\/agrave.glif","\/Labtop Unicase.ufo\/glyphs\/ampersand.glif":"\/Labtop Unicase.ufo\/glyphs\/ampersand.glif","\/Labtop Unicase.ufo\/glyphs\/apple.glif":"\/Labtop Unicase.ufo\/glyphs\/apple.glif","\/Labtop Unicase.ufo\/glyphs\/aring.glif":"\/Labtop Unicase.ufo\/glyphs\/aring.glif","\/Labtop Unicase.ufo\/glyphs\/asciicircum.glif":"\/Labtop Unicase.ufo\/glyphs\/asciicircum.glif","\/Labtop Unicase.ufo\/glyphs\/asciitilde.glif":"\/Labtop Unicase.ufo\/glyphs\/asciitilde.glif","\/Labtop Unicase.ufo\/glyphs\/asterisk.glif":"\/Labtop Unicase.ufo\/glyphs\/asterisk.glif","\/Labtop Unicase.ufo\/glyphs\/at.glif":"\/Labtop Unicase.ufo\/glyphs\/at.glif","\/Labtop Unicase.ufo\/glyphs\/atilde.glif":"\/Labtop Unicase.ufo\/glyphs\/atilde.glif","\/Labtop Unicase.ufo\/glyphs\/b.glif":"\/Labtop Unicase.ufo\/glyphs\/b.glif","\/Labtop Unicase.ufo\/glyphs\/backslash.glif":"\/Labtop Unicase.ufo\/glyphs\/backslash.glif","\/Labtop Unicase.ufo\/glyphs\/bar.glif":"\/Labtop Unicase.ufo\/glyphs\/bar.glif","\/Labtop Unicase.ufo\/glyphs\/braceleft.glif":"\/Labtop Unicase.ufo\/glyphs\/braceleft.glif","\/Labtop Unicase.ufo\/glyphs\/braceright.glif":"\/Labtop Unicase.ufo\/glyphs\/braceright.glif","\/Labtop Unicase.ufo\/glyphs\/bracketleft.glif":"\/Labtop Unicase.ufo\/glyphs\/bracketleft.glif","\/Labtop Unicase.ufo\/glyphs\/bracketright.glif":"\/Labtop Unicase.ufo\/glyphs\/bracketright.glif","\/Labtop Unicase.ufo\/glyphs\/brokenbar.glif":"\/Labtop Unicase.ufo\/glyphs\/brokenbar.glif","\/Labtop Unicase.ufo\/glyphs\/bullet.glif":"\/Labtop Unicase.ufo\/glyphs\/bullet.glif","\/Labtop Unicase.ufo\/glyphs\/c.glif":"\/Labtop Unicase.ufo\/glyphs\/c.glif","\/Labtop Unicase.ufo\/glyphs\/caron.glif":"\/Labtop Unicase.ufo\/glyphs\/caron.glif","\/Labtop Unicase.ufo\/glyphs\/ccedilla.glif":"\/Labtop Unicase.ufo\/glyphs\/ccedilla.glif","\/Labtop Unicase.ufo\/glyphs\/cedilla.glif":"\/Labtop Unicase.ufo\/glyphs\/cedilla.glif","\/Labtop Unicase.ufo\/glyphs\/cent.glif":"\/Labtop Unicase.ufo\/glyphs\/cent.glif","\/Labtop Unicase.ufo\/glyphs\/circumflex.glif":"\/Labtop Unicase.ufo\/glyphs\/circumflex.glif","\/Labtop Unicase.ufo\/glyphs\/colon.glif":"\/Labtop Unicase.ufo\/glyphs\/colon.glif","\/Labtop Unicase.ufo\/glyphs\/comma.glif":"\/Labtop Unicase.ufo\/glyphs\/comma.glif","\/Labtop Unicase.ufo\/glyphs\/contents.plist":"\/Labtop Unicase.ufo\/glyphs\/contents.plist","\/Labtop Unicase.ufo\/glyphs\/copyright.glif":"\/Labtop Unicase.ufo\/glyphs\/copyright.glif","\/Labtop Unicase.ufo\/glyphs\/currency.glif":"\/Labtop Unicase.ufo\/glyphs\/currency.glif","\/Labtop Unicase.ufo\/glyphs\/d.glif":"\/Labtop Unicase.ufo\/glyphs\/d.glif","\/Labtop Unicase.ufo\/glyphs\/dagger.glif":"\/Labtop Unicase.ufo\/glyphs\/dagger.glif","\/Labtop Unicase.ufo\/glyphs\/daggerdbl.glif":"\/Labtop Unicase.ufo\/glyphs\/daggerdbl.glif","\/Labtop Unicase.ufo\/glyphs\/degree.glif":"\/Labtop Unicase.ufo\/glyphs\/degree.glif","\/Labtop Unicase.ufo\/glyphs\/dieresis.glif":"\/Labtop Unicase.ufo\/glyphs\/dieresis.glif","\/Labtop Unicase.ufo\/glyphs\/divide.glif":"\/Labtop Unicase.ufo\/glyphs\/divide.glif","\/Labtop Unicase.ufo\/glyphs\/dollar.glif":"\/Labtop Unicase.ufo\/glyphs\/dollar.glif","\/Labtop Unicase.ufo\/glyphs\/dotlessi.glif":"\/Labtop Unicase.ufo\/glyphs\/dotlessi.glif","\/Labtop Unicase.ufo\/glyphs\/e.glif":"\/Labtop Unicase.ufo\/glyphs\/e.glif","\/Labtop Unicase.ufo\/glyphs\/eacute.glif":"\/Labtop Unicase.ufo\/glyphs\/eacute.glif","\/Labtop Unicase.ufo\/glyphs\/ecircumflex.glif":"\/Labtop Unicase.ufo\/glyphs\/ecircumflex.glif","\/Labtop Unicase.ufo\/glyphs\/edieresis.glif":"\/Labtop Unicase.ufo\/glyphs\/edieresis.glif","\/Labtop Unicase.ufo\/glyphs\/egrave.glif":"\/Labtop Unicase.ufo\/glyphs\/egrave.glif","\/Labtop Unicase.ufo\/glyphs\/eight.glif":"\/Labtop Unicase.ufo\/glyphs\/eight.glif","\/Labtop Unicase.ufo\/glyphs\/ellipsis.glif":"\/Labtop Unicase.ufo\/glyphs\/ellipsis.glif","\/Labtop Unicase.ufo\/glyphs\/emdash.glif":"\/Labtop Unicase.ufo\/glyphs\/emdash.glif","\/Labtop Unicase.ufo\/glyphs\/endash.glif":"\/Labtop Unicase.ufo\/glyphs\/endash.glif","\/Labtop Unicase.ufo\/glyphs\/equal.glif":"\/Labtop Unicase.ufo\/glyphs\/equal.glif","\/Labtop Unicase.ufo\/glyphs\/eth.glif":"\/Labtop Unicase.ufo\/glyphs\/eth.glif","\/Labtop Unicase.ufo\/glyphs\/exclam.glif":"\/Labtop Unicase.ufo\/glyphs\/exclam.glif","\/Labtop Unicase.ufo\/glyphs\/exclamdown.glif":"\/Labtop Unicase.ufo\/glyphs\/exclamdown.glif","\/Labtop Unicase.ufo\/glyphs\/f.glif":"\/Labtop Unicase.ufo\/glyphs\/f.glif","\/Labtop Unicase.ufo\/glyphs\/five.glif":"\/Labtop Unicase.ufo\/glyphs\/five.glif","\/Labtop Unicase.ufo\/glyphs\/florin.glif":"\/Labtop Unicase.ufo\/glyphs\/florin.glif","\/Labtop Unicase.ufo\/glyphs\/four.glif":"\/Labtop Unicase.ufo\/glyphs\/four.glif","\/Labtop Unicase.ufo\/glyphs\/g.glif":"\/Labtop Unicase.ufo\/glyphs\/g.glif","\/Labtop Unicase.ufo\/glyphs\/germandbls.glif":"\/Labtop Unicase.ufo\/glyphs\/germandbls.glif","\/Labtop Unicase.ufo\/glyphs\/grave.glif":"\/Labtop Unicase.ufo\/glyphs\/grave.glif","\/Labtop Unicase.ufo\/glyphs\/greater.glif":"\/Labtop Unicase.ufo\/glyphs\/greater.glif","\/Labtop Unicase.ufo\/glyphs\/guillemotleft.glif":"\/Labtop Unicase.ufo\/glyphs\/guillemotleft.glif","\/Labtop Unicase.ufo\/glyphs\/guillemotright.glif":"\/Labtop Unicase.ufo\/glyphs\/guillemotright.glif","\/Labtop Unicase.ufo\/glyphs\/guilsinglleft.glif":"\/Labtop Unicase.ufo\/glyphs\/guilsinglleft.glif","\/Labtop Unicase.ufo\/glyphs\/guilsinglright.glif":"\/Labtop Unicase.ufo\/glyphs\/guilsinglright.glif","\/Labtop Unicase.ufo\/glyphs\/h.glif":"\/Labtop Unicase.ufo\/glyphs\/h.glif","\/Labtop Unicase.ufo\/glyphs\/hyphen.glif":"\/Labtop Unicase.ufo\/glyphs\/hyphen.glif","\/Labtop Unicase.ufo\/glyphs\/i.glif":"\/Labtop Unicase.ufo\/glyphs\/i.glif","\/Labtop Unicase.ufo\/glyphs\/iacute.glif":"\/Labtop Unicase.ufo\/glyphs\/iacute.glif","\/Labtop Unicase.ufo\/glyphs\/icircumflex.glif":"\/Labtop Unicase.ufo\/glyphs\/icircumflex.glif","\/Labtop Unicase.ufo\/glyphs\/idieresis.glif":"\/Labtop Unicase.ufo\/glyphs\/idieresis.glif","\/Labtop Unicase.ufo\/glyphs\/igrave.glif":"\/Labtop Unicase.ufo\/glyphs\/igrave.glif","\/Labtop Unicase.ufo\/glyphs\/j.glif":"\/Labtop Unicase.ufo\/glyphs\/j.glif","\/Labtop Unicase.ufo\/glyphs\/k.glif":"\/Labtop Unicase.ufo\/glyphs\/k.glif","\/Labtop Unicase.ufo\/glyphs\/l.glif":"\/Labtop Unicase.ufo\/glyphs\/l.glif","\/Labtop Unicase.ufo\/glyphs\/less.glif":"\/Labtop Unicase.ufo\/glyphs\/less.glif","\/Labtop Unicase.ufo\/glyphs\/logicalnot.glif":"\/Labtop Unicase.ufo\/glyphs\/logicalnot.glif","\/Labtop Unicase.ufo\/glyphs\/lslash.glif":"\/Labtop Unicase.ufo\/glyphs\/lslash.glif","\/Labtop Unicase.ufo\/glyphs\/m.glif":"\/Labtop Unicase.ufo\/glyphs\/m.glif","\/Labtop Unicase.ufo\/glyphs\/macron.glif":"\/Labtop Unicase.ufo\/glyphs\/macron.glif","\/Labtop Unicase.ufo\/glyphs\/minus.glif":"\/Labtop Unicase.ufo\/glyphs\/minus.glif","\/Labtop Unicase.ufo\/glyphs\/mu.glif":"\/Labtop Unicase.ufo\/glyphs\/mu.glif","\/Labtop Unicase.ufo\/glyphs\/multiply.glif":"\/Labtop Unicase.ufo\/glyphs\/multiply.glif","\/Labtop Unicase.ufo\/glyphs\/n.glif":"\/Labtop Unicase.ufo\/glyphs\/n.glif","\/Labtop Unicase.ufo\/glyphs\/nine.glif":"\/Labtop Unicase.ufo\/glyphs\/nine.glif","\/Labtop Unicase.ufo\/glyphs\/nonmarkingreturn.glif":"\/Labtop Unicase.ufo\/glyphs\/nonmarkingreturn.glif","\/Labtop Unicase.ufo\/glyphs\/ntilde.glif":"\/Labtop Unicase.ufo\/glyphs\/ntilde.glif","\/Labtop Unicase.ufo\/glyphs\/numbersign.glif":"\/Labtop Unicase.ufo\/glyphs\/numbersign.glif","\/Labtop Unicase.ufo\/glyphs\/o.glif":"\/Labtop Unicase.ufo\/glyphs\/o.glif","\/Labtop Unicase.ufo\/glyphs\/oacute.glif":"\/Labtop Unicase.ufo\/glyphs\/oacute.glif","\/Labtop Unicase.ufo\/glyphs\/ocircumflex.glif":"\/Labtop Unicase.ufo\/glyphs\/ocircumflex.glif","\/Labtop Unicase.ufo\/glyphs\/odieresis.glif":"\/Labtop Unicase.ufo\/glyphs\/odieresis.glif","\/Labtop Unicase.ufo\/glyphs\/oe.glif":"\/Labtop Unicase.ufo\/glyphs\/oe.glif","\/Labtop Unicase.ufo\/glyphs\/ograve.glif":"\/Labtop Unicase.ufo\/glyphs\/ograve.glif","\/Labtop Unicase.ufo\/glyphs\/one.glif":"\/Labtop Unicase.ufo\/glyphs\/one.glif","\/Labtop Unicase.ufo\/glyphs\/onehalf.glif":"\/Labtop Unicase.ufo\/glyphs\/onehalf.glif","\/Labtop Unicase.ufo\/glyphs\/onequarter.glif":"\/Labtop Unicase.ufo\/glyphs\/onequarter.glif","\/Labtop Unicase.ufo\/glyphs\/onesuperior.glif":"\/Labtop Unicase.ufo\/glyphs\/onesuperior.glif","\/Labtop Unicase.ufo\/glyphs\/ordfeminine.glif":"\/Labtop Unicase.ufo\/glyphs\/ordfeminine.glif","\/Labtop Unicase.ufo\/glyphs\/ordmasculine.glif":"\/Labtop Unicase.ufo\/glyphs\/ordmasculine.glif","\/Labtop Unicase.ufo\/glyphs\/oslash.glif":"\/Labtop Unicase.ufo\/glyphs\/oslash.glif","\/Labtop Unicase.ufo\/glyphs\/otilde.glif":"\/Labtop Unicase.ufo\/glyphs\/otilde.glif","\/Labtop Unicase.ufo\/glyphs\/p.glif":"\/Labtop Unicase.ufo\/glyphs\/p.glif","\/Labtop Unicase.ufo\/glyphs\/paragraph.glif":"\/Labtop Unicase.ufo\/glyphs\/paragraph.glif","\/Labtop Unicase.ufo\/glyphs\/parenleft.glif":"\/Labtop Unicase.ufo\/glyphs\/parenleft.glif","\/Labtop Unicase.ufo\/glyphs\/parenright.glif":"\/Labtop Unicase.ufo\/glyphs\/parenright.glif","\/Labtop Unicase.ufo\/glyphs\/percent.glif":"\/Labtop Unicase.ufo\/glyphs\/percent.glif","\/Labtop Unicase.ufo\/glyphs\/period.glif":"\/Labtop Unicase.ufo\/glyphs\/period.glif","\/Labtop Unicase.ufo\/glyphs\/periodcentered.glif":"\/Labtop Unicase.ufo\/glyphs\/periodcentered.glif","\/Labtop Unicase.ufo\/glyphs\/perthousand.glif":"\/Labtop Unicase.ufo\/glyphs\/perthousand.glif","\/Labtop Unicase.ufo\/glyphs\/plus.glif":"\/Labtop Unicase.ufo\/glyphs\/plus.glif","\/Labtop Unicase.ufo\/glyphs\/plusminus.glif":"\/Labtop Unicase.ufo\/glyphs\/plusminus.glif","\/Labtop Unicase.ufo\/glyphs\/q.glif":"\/Labtop Unicase.ufo\/glyphs\/q.glif","\/Labtop Unicase.ufo\/glyphs\/question.glif":"\/Labtop Unicase.ufo\/glyphs\/question.glif","\/Labtop Unicase.ufo\/glyphs\/questiondown.glif":"\/Labtop Unicase.ufo\/glyphs\/questiondown.glif","\/Labtop Unicase.ufo\/glyphs\/quotedbl.glif":"\/Labtop Unicase.ufo\/glyphs\/quotedbl.glif","\/Labtop Unicase.ufo\/glyphs\/quotedblbase.glif":"\/Labtop Unicase.ufo\/glyphs\/quotedblbase.glif","\/Labtop Unicase.ufo\/glyphs\/quotedblleft.glif":"\/Labtop Unicase.ufo\/glyphs\/quotedblleft.glif","\/Labtop Unicase.ufo\/glyphs\/quotedblright.glif":"\/Labtop Unicase.ufo\/glyphs\/quotedblright.glif","\/Labtop Unicase.ufo\/glyphs\/quoteleft.glif":"\/Labtop Unicase.ufo\/glyphs\/quoteleft.glif","\/Labtop Unicase.ufo\/glyphs\/quoteright.glif":"\/Labtop Unicase.ufo\/glyphs\/quoteright.glif","\/Labtop Unicase.ufo\/glyphs\/quotesinglbase.glif":"\/Labtop Unicase.ufo\/glyphs\/quotesinglbase.glif","\/Labtop Unicase.ufo\/glyphs\/quotesingle.glif":"\/Labtop Unicase.ufo\/glyphs\/quotesingle.glif","\/Labtop Unicase.ufo\/glyphs\/r.glif":"\/Labtop Unicase.ufo\/glyphs\/r.glif","\/Labtop Unicase.ufo\/glyphs\/registered.glif":"\/Labtop Unicase.ufo\/glyphs\/registered.glif","\/Labtop Unicase.ufo\/glyphs\/s.glif":"\/Labtop Unicase.ufo\/glyphs\/s.glif","\/Labtop Unicase.ufo\/glyphs\/scaron.glif":"\/Labtop Unicase.ufo\/glyphs\/scaron.glif","\/Labtop Unicase.ufo\/glyphs\/section.glif":"\/Labtop Unicase.ufo\/glyphs\/section.glif","\/Labtop Unicase.ufo\/glyphs\/semicolon.glif":"\/Labtop Unicase.ufo\/glyphs\/semicolon.glif","\/Labtop Unicase.ufo\/glyphs\/seven.glif":"\/Labtop Unicase.ufo\/glyphs\/seven.glif","\/Labtop Unicase.ufo\/glyphs\/six.glif":"\/Labtop Unicase.ufo\/glyphs\/six.glif","\/Labtop Unicase.ufo\/glyphs\/slash.glif":"\/Labtop Unicase.ufo\/glyphs\/slash.glif","\/Labtop Unicase.ufo\/glyphs\/space.glif":"\/Labtop Unicase.ufo\/glyphs\/space.glif","\/Labtop Unicase.ufo\/glyphs\/sterling.glif":"\/Labtop Unicase.ufo\/glyphs\/sterling.glif","\/Labtop Unicase.ufo\/glyphs\/t.glif":"\/Labtop Unicase.ufo\/glyphs\/t.glif","\/Labtop Unicase.ufo\/glyphs\/thorn.glif":"\/Labtop Unicase.ufo\/glyphs\/thorn.glif","\/Labtop Unicase.ufo\/glyphs\/three.glif":"\/Labtop Unicase.ufo\/glyphs\/three.glif","\/Labtop Unicase.ufo\/glyphs\/threequarters.glif":"\/Labtop Unicase.ufo\/glyphs\/threequarters.glif","\/Labtop Unicase.ufo\/glyphs\/threesuperior.glif":"\/Labtop Unicase.ufo\/glyphs\/threesuperior.glif","\/Labtop Unicase.ufo\/glyphs\/tilde.glif":"\/Labtop Unicase.ufo\/glyphs\/tilde.glif","\/Labtop Unicase.ufo\/glyphs\/trademark.glif":"\/Labtop Unicase.ufo\/glyphs\/trademark.glif","\/Labtop Unicase.ufo\/glyphs\/two.glif":"\/Labtop Unicase.ufo\/glyphs\/two.glif","\/Labtop Unicase.ufo\/glyphs\/twosuperior.glif":"\/Labtop Unicase.ufo\/glyphs\/twosuperior.glif","\/Labtop Unicase.ufo\/glyphs\/u.glif":"\/Labtop Unicase.ufo\/glyphs\/u.glif","\/Labtop Unicase.ufo\/glyphs\/uacute.glif":"\/Labtop Unicase.ufo\/glyphs\/uacute.glif","\/Labtop Unicase.ufo\/glyphs\/ucircumflex.glif":"\/Labtop Unicase.ufo\/glyphs\/ucircumflex.glif","\/Labtop Unicase.ufo\/glyphs\/udieresis.glif":"\/Labtop Unicase.ufo\/glyphs\/udieresis.glif","\/Labtop Unicase.ufo\/glyphs\/ugrave.glif":"\/Labtop Unicase.ufo\/glyphs\/ugrave.glif","\/Labtop Unicase.ufo\/glyphs\/underscore.glif":"\/Labtop Unicase.ufo\/glyphs\/underscore.glif","\/Labtop Unicase.ufo\/glyphs\/v.glif":"\/Labtop Unicase.ufo\/glyphs\/v.glif","\/Labtop Unicase.ufo\/glyphs\/w.glif":"\/Labtop Unicase.ufo\/glyphs\/w.glif","\/Labtop Unicase.ufo\/glyphs\/x.glif":"\/Labtop Unicase.ufo\/glyphs\/x.glif","\/Labtop Unicase.ufo\/glyphs\/y.glif":"\/Labtop Unicase.ufo\/glyphs\/y.glif","\/Labtop Unicase.ufo\/glyphs\/yacute.glif":"\/Labtop Unicase.ufo\/glyphs\/yacute.glif","\/Labtop Unicase.ufo\/glyphs\/ydieresis.glif":"\/Labtop Unicase.ufo\/glyphs\/ydieresis.glif","\/Labtop Unicase.ufo\/glyphs\/yen.glif":"\/Labtop Unicase.ufo\/glyphs\/yen.glif","\/Labtop Unicase.ufo\/glyphs\/z.glif":"\/Labtop Unicase.ufo\/glyphs\/z.glif","\/Labtop Unicase.ufo\/glyphs\/zcaron.glif":"\/Labtop Unicase.ufo\/glyphs\/zcaron.glif","\/Labtop Unicase.ufo\/glyphs\/zero.glif":"\/Labtop Unicase.ufo\/glyphs\/zero.glif","\/TCPDF (PHP Extension)\/labtop unicase.php":"\/TCPDF (PHP Extension)\/labtop unicase.php","\/TCPDF (PHP Extension)\/labtop unicase.z":"\/TCPDF (PHP Extension)\/labtop unicase.z"},"Upload":{"name":"Lukey Shaw","company":"Lukey Shaw","email":"lukey@snails.email","twitter":"fonts4web"},"Table":{"FFTM":{"entryLength":16,"tag":"FFTM","checksum":2006860680,"offset":20700,"length":28},"GDEF":{"entryLength":16,"tag":"GDEF","checksum":17629188,"offset":20668,"length":32},"OS\/2":{"entryLength":16,"tag":"OS\/2","checksum":1466171691,"offset":344,"length":86},"cmap":{"entryLength":16,"tag":"cmap","checksum":484192534,"offset":1328,"length":514},"gasp":{"entryLength":16,"tag":"gasp","checksum":4294901763,"offset":20660,"length":8},"glyf":{"entryLength":16,"tag":"glyf","checksum":4146569364,"offset":2296,"length":16560},"head":{"entryLength":16,"tag":"head","checksum":238691823,"offset":220,"length":54},"hhea":{"entryLength":16,"tag":"hhea","checksum":125174528,"offset":276,"length":36},"hmtx":{"entryLength":16,"tag":"hmtx","checksum":89201808,"offset":432,"length":896},"loca":{"entryLength":16,"tag":"loca","checksum":3345135628,"offset":1844,"length":450},"maxp":{"entryLength":16,"tag":"maxp","checksum":19464289,"offset":312,"length":32},"name":{"entryLength":16,"tag":"name","checksum":3436854312,"offset":18856,"length":1317},"post":{"entryLength":16,"tag":"post","checksum":885732021,"offset":20176,"length":482}},"UnicodeCharMap":{"0":1,"13":2,"32":3,"33":4,"34":5,"35":6,"36":7,"37":8,"38":9,"39":10,"40":11,"41":12,"42":13,"43":14,"44":15,"45":16,"46":17,"47":18,"48":19,"49":20,"50":21,"51":22,"52":23,"53":24,"54":25,"55":26,"56":27,"57":28,"58":29,"59":30,"60":31,"61":32,"62":33,"63":34,"64":35,"65":36,"66":37,"67":38,"68":39,"69":40,"70":41,"71":42,"72":43,"73":44,"74":45,"75":46,"76":47,"77":48,"78":49,"79":50,"80":51,"81":52,"82":53,"83":54,"84":55,"85":56,"86":57,"87":58,"88":59,"89":60,"90":61,"91":62,"92":63,"93":64,"94":65,"95":66,"96":67,"97":68,"98":69,"99":70,"100":71,"101":72,"102":73,"103":74,"104":75,"105":76,"106":77,"107":78,"108":79,"109":80,"110":81,"111":82,"112":83,"113":84,"114":85,"115":86,"116":87,"117":88,"118":89,"119":90,"120":91,"121":92,"122":93,"123":94,"124":95,"125":96,"126":97,"161":98,"162":99,"163":100,"164":101,"165":102,"166":103,"167":104,"168":105,"169":106,"170":107,"171":108,"172":109,"174":110,"175":111,"176":112,"177":113,"178":114,"179":115,"180":116,"182":117,"183":118,"184":119,"185":120,"186":121,"187":122,"188":123,"189":124,"190":125,"191":126,"192":127,"193":128,"194":129,"195":130,"196":131,"197":132,"198":133,"199":134,"200":135,"201":136,"202":137,"203":138,"204":139,"205":140,"206":141,"207":142,"208":143,"209":144,"210":145,"211":146,"212":147,"213":148,"214":149,"215":150,"216":151,"217":152,"218":153,"219":154,"220":155,"221":156,"222":157,"223":158,"224":159,"225":160,"226":161,"227":162,"228":163,"229":164,"230":165,"231":166,"232":167,"233":168,"234":169,"235":170,"236":171,"237":172,"238":173,"239":174,"240":175,"241":176,"242":177,"243":178,"244":179,"245":180,"246":181,"247":182,"248":183,"249":184,"250":185,"251":186,"252":187,"253":188,"254":189,"255":190,"305":191,"321":192,"322":193,"338":194,"339":195,"352":196,"353":197,"376":198,"381":199,"382":200,"402":201,"710":202,"711":203,"732":204,"956":205,"8211":206,"8212":207,"8216":208,"8217":209,"8218":210,"8220":211,"8221":212,"8222":213,"8224":214,"8225":215,"8226":216,"8230":217,"8240":218,"8249":219,"8250":220,"8482":221,"8722":222},"Name":"Labtop Unicase","Tags":[""],"barcode":"e42wo","referee":"q53wakyemyk"}